vac_aligner/__init__.py
vac_aligner/dto.py
vac_aligner/factory.py
vac_aligner/vac_pipeline.py
vac_aligner/asr/__init__.py
vac_aligner/asr/batch_inference.py
vac_aligner/data/matching/test_with_predictions17_replaced.json
vac_aligner/matching/__init__.py
vac_aligner/matching/align.py
vac_aligner/matching/benchmark_on_mcv.py
vac_aligner/matching/cutting.py
vac_aligner/matching/metrics.py
vac_aligner/matching/utils.py
vac_aligner/vad/__init__.py
vac_aligner-0.0.4.dist-info/AUTHORS.rst
vac_aligner-0.0.4.dist-info/LICENSE
vac_aligner-0.0.4.dist-info/METADATA
vac_aligner-0.0.4.dist-info/WHEEL
vac_aligner-0.0.4.dist-info/top_level.txt
vac_aligner-0.0.4.dist-info/RECORD
