Metadata-Version: 2.1
Name: vac_aligner
Version: 0.0.4
Summary: Aligning Very Long audio and text pairs through VAC pipeline
Home-page: https://github.com/Ara-Yeroyan/vac_aligner
Download-URL: https://github.com/Ara-Yeroyan/vac_aligner/archive/refs/tags/v0.0.2.tar.gz
Author: Ara Yeroyan
Author-email: ar23yeroyan@gmail.com
License: Apache Software License 2.0
Keywords: vac_aligner
Classifier: Development Status :: 2 - Pre-Alpha
Classifier: Intended Audience :: Developers
Classifier: License :: OSI Approved :: Apache Software License
Classifier: Natural Language :: English
Classifier: Programming Language :: Python :: 3.10
Classifier: Programming Language :: Python :: 3.11
Classifier: Programming Language :: Python :: 3.12
Requires-Python: >=3.10
License-File: LICENSE
License-File: AUTHORS.rst
Requires-Dist: pandas ~=2.0.3
Requires-Dist: regex ~=2024.5.15
Requires-Dist: tqdm ~=4.66.4
Requires-Dist: loguru ~=0.7.2
Requires-Dist: setuptools ~=70.0.0
Provides-Extra: full
Requires-Dist: nemo-toolkit[asr] ; extra == 'full'
